Orange_Spectroscopy-0.9.1-py3.11-nspkg.pth
orange_spectroscopy-0.9.1.dist-info/licenses/LICENSE
orangecontrib/spectroscopy/__init__.py
orangecontrib/spectroscopy/data.py
orangecontrib/spectroscopy/irfft.py
orangecontrib/spectroscopy/util.py
orangecontrib/spectroscopy/datasets/Au168mA_nodisplacement.gsf
orangecontrib/spectroscopy/datasets/IFG_single.dpt
orangecontrib/spectroscopy/datasets/__init__.py
orangecontrib/spectroscopy/datasets/collagen.csv
orangecontrib/spectroscopy/datasets/exafs-test.tab
orangecontrib/spectroscopy/datasets/m_xyxy.spc
orangecontrib/spectroscopy/datasets/map_test.xyz
orangecontrib/spectroscopy/datasets/max_iv.hdr
orangecontrib/spectroscopy/datasets/max_iv_a000.xim
orangecontrib/spectroscopy/datasets/max_iv_a001.xim
orangecontrib/spectroscopy/datasets/nea_test_v2.txt
orangecontrib/spectroscopy/datasets/peach_juice.0
orangecontrib/spectroscopy/datasets/peach_juice.dpt
orangecontrib/spectroscopy/datasets/rock.txt
orangecontrib/spectroscopy/datasets/sample1.spa
orangecontrib/spectroscopy/datasets/small_Omnic.map
orangecontrib/spectroscopy/datasets/small_diamond_nxs.nxs
orangecontrib/spectroscopy/datasets/spectra20_small.nea
orangecontrib/spectroscopy/datasets/three_coordinates_data.csv
orangecontrib/spectroscopy/datasets/whitelight.gsf
orangecontrib/spectroscopy/datasets/Hermes_HDF5/small_OK.hdf5
orangecontrib/spectroscopy/datasets/NeaReaderGSF_test/NeaReaderGSF_test O2A raw.gsf
orangecontrib/spectroscopy/datasets/NeaReaderGSF_test/NeaReaderGSF_test O2P raw.gsf
orangecontrib/spectroscopy/datasets/NeaReaderGSF_test/NeaReaderGSF_test.html
orangecontrib/spectroscopy/datasets/NeaReaderMultichannel_test/Test_Au_Fourier_Scan_Synchrotron.txt
orangecontrib/spectroscopy/datasets/agilent/4_noimage_agg256.bsp
orangecontrib/spectroscopy/datasets/agilent/4_noimage_agg256.dat
orangecontrib/spectroscopy/datasets/agilent/4_noimage_agg256.hdr
orangecontrib/spectroscopy/datasets/agilent/4_noimage_agg256.seq
orangecontrib/spectroscopy/datasets/agilent/5_Mosaic_agg1024.dat
orange_spectroscopy-0.9.1.dist-info/METADATA
orange_spectroscopy-0.9.1.dist-info/WHEEL
orange_spectroscopy-0.9.1.dist-info/entry_points.txt
orange_spectroscopy-0.9.1.dist-info/namespace_packages.txt
orange_spectroscopy-0.9.1.dist-info/top_level.txt
orange_spectroscopy-0.9.1.dist-info/RECORD
